README.md
setup.cfg
setup.py
synaptor/__init__.py
synaptor/diagnostics.py
synaptor.egg-info/PKG-INFO
synaptor.egg-info/SOURCES.txt
synaptor.egg-info/dependency_links.txt
synaptor.egg-info/not-zip-safe
synaptor.egg-info/requires.txt
synaptor.egg-info/top_level.txt
synaptor/evaluate/__init__.py
synaptor/evaluate/cremi.py
synaptor/evaluate/edge.py
synaptor/evaluate/gridsearch.py
synaptor/evaluate/overlap.py
synaptor/evaluate/partnerprox.py
synaptor/evaluate/score.py
synaptor/evaluate/auto/__init__.py
synaptor/evaluate/auto/auto.py
synaptor/evaluate/auto/dataset.py
synaptor/evaluate/auto/toolbox.py
synaptor/io/__init__.py
synaptor/io/base.py
synaptor/io/utils.py
synaptor/io/backends/__init__.py
synaptor/io/backends/aws.py
synaptor/io/backends/cloudvolume.py
synaptor/io/backends/gcloud.py
synaptor/io/backends/local.py
synaptor/io/backends/sqlalchemy.py
synaptor/io/backends/utils.py
synaptor/proc/__init__.py
synaptor/proc/colnames.py
synaptor/proc/hashing.py
synaptor/proc/tasks.py
synaptor/proc/tasks_w_io.py
synaptor/proc/utils.py
synaptor/proc/anchor/__init__.py
synaptor/proc/anchor/anchor.py
synaptor/proc/anchor/edgepoints.py
synaptor/proc/anchor/merge.py
synaptor/proc/candidate/__init__.py
synaptor/proc/candidate/candidates.py
synaptor/proc/candidate/cleft.py
synaptor/proc/candidate/partnerprox.py
synaptor/proc/edge/__init__.py
synaptor/proc/edge/assign.py
synaptor/proc/edge/asynet.py
synaptor/proc/edge/cremi.py
synaptor/proc/edge/dataset.py
synaptor/proc/edge/info.py
synaptor/proc/edge/locs.py
synaptor/proc/edge/misc.py
synaptor/proc/edge/pruner.py
synaptor/proc/edge/score.py
synaptor/proc/edge/thresholded.py
synaptor/proc/edge/merge/__init__.py
synaptor/proc/edge/merge/edges.py
synaptor/proc/edge/merge/merge_df.py
synaptor/proc/edge/merge/merge_dups.py
synaptor/proc/edge/merge/misc.py
synaptor/proc/edge/single_edges/__init__.py
synaptor/proc/edge/single_edges/pruner.py
synaptor/proc/edge/single_edges/pull.py
synaptor/proc/io/__init__.py
synaptor/proc/io/continuation.py
synaptor/proc/io/edgeinfo.py
synaptor/proc/io/filenames.py
synaptor/proc/io/fullinfo.py
synaptor/proc/io/idmap.py
synaptor/proc/io/initdb.py
synaptor/proc/io/network.py
