Metadata-Version: 1.0
Name: synaptor
Version: 0.0.1
Summary: Prediction of synaptic clefts synaptic connectivity inference for connectomics
Home-page: https://github.com/nicholasturner1/Synaptor
Author: Nicholas Turner
Author-email: nturner@cs.princeton.edu
License: UNKNOWN
Platform: UNKNOWN
